array_normal_84/Arraymul_eight_four.v
module FA(sum,cout,a,b,cin);

    input a,b,cin;
    output sum,cout;

    assign sum=(a^b^cin);
    assign cout= (a&b)|(b&cin)|(a&cin);

endmodule

module PP(pc,c,d);

    input c,d;
    output pc;

    assign pc= c&d;

endmodule

module Arraymul_eight_four (
    input [7:0]A,
    input [3:0]B,
    output [11:0] R 
);

    wire [64:0]s,c;   //for sum and carry bits
    wire [7:0]pp;    //for partial product calculation

    //row0 --- calculation of partial product block

    PP PP01(pp[0],A[0],B[0]);
    PP PP02(pp[1],A[1],B[0]);
    PP PP03(pp[2],A[2],B[0]);
    PP PP04(pp[3],A[3],B[0]);
    PP PP05(pp[4],A[4],B[0]);
    PP PP06(pp[5],A[5],B[0]);
    PP PP07(pp[6],A[6],B[0]);
    PP PP08(pp[7],A[7],B[0]);

    //row1

    FA FA11(s[0],c[0],(A[0]&B[1]),pp[1],1'b0);
    FA FA12(s[1],c[1],(A[1]&B[1]),pp[2],c[0]);
    FA FA13(s[2],c[2],(A[2]&B[1]),pp[3],c[1]);
    FA FA14(s[3],c[3],(A[3]&B[1]),pp[4],c[2]);
    FA FA15(s[4],c[4],(A[4]&B[1]),pp[5],c[3]);
    FA FA16(s[5],c[5],(A[5]&B[1]),pp[6],c[4]);
    FA FA17(s[6],c[6],(A[6]&B[1]),pp[7],c[5]);
    FA FA18(s[7],c[7],(A[7]&B[1]),1'b0,c[6]);

    //row2
    FA FA21(s[8],c[8],(A[0]&B[2]),s[1],1'b0);
    FA FA22(s[9],c[9],(A[1]&B[2]),s[2],c[8]);
    FA FA23(s[10],c[10],(A[2]&B[2]),s[3],c[9]);
    FA FA24(s[11],c[11],(A[3]&B[2]),s[4],c[10]);
    FA FA25(s[12],c[12],(A[4]&B[2]),s[5],c[11]);
    FA FA26(s[13],c[13],(A[5]&B[2]),s[6],c[12]);
    FA FA27(s[14],c[14],(A[6]&B[2]),s[7],c[13]);
    FA FA28(s[15],c[15],(A[7]&B[2]),c[7],c[14]);

    //row3
    FA FA31(s[16],c[16],(A[0]&B[3]),s[9],1'b0);
    FA FA32(s[17],c[17],(A[1]&B[3]),s[10],c[16]);
    FA FA33(s[18],c[18],(A[2]&B[3]),s[11],c[17]);
    FA FA34(s[19],c[19],(A[3]&B[3]),s[12],c[18]);
    FA FA35(s[20],c[20],(A[4]&B[3]),s[13],c[19]);
    FA FA36(s[21],c[21],(A[5]&B[3]),s[14],c[20]);
    FA FA37(s[22],c[22],(A[6]&B[3]),s[15],c[21]);
    FA FA38(s[23],c[23],(A[7]&B[3]),c[15],c[22]);

    assign R[0] = pp[0];
    assign R[1] = s[0];
    assign R[2] = s[8];
    assign R[3] = s[16];
    assign R[4] = s[17];
    assign R[5] = s[18];
    assign R[6] = s[19];
    assign R[7] = s[20];
    assign R[8] = s[21];
    assign R[9] = s[22];
    assign R[10] = s[23];
    assign R[11] = c[23];

endmodule

array_normal_84/Arraymul_eight_four_tb.v
`timescale 1ns/1ns
`include "Arraymul_eight_four.v"

module Arraymul_eight_four_tb;

reg [7:0] A;
reg [3:0] B;
wire [11:0] R;

Arraymul_eight_four uut(.A(A), .B(B), .R(R));

// Iterate over all possible 8-bit values for A and B
integer i;
integer j;

// Open a file for writing
integer file_id;

initial begin
    
    file_id = $fopen("output2.txt", "w");
    if (file_id == 0) begin
        $display("Error opening file for writing");
        $finish;
    end
    
    $dumpfile("Arraymul_eight_four_tb.vcd");
    $dumpvars(0, Arraymul_eight_four_tb);
    

    for (i = 0; i < 256; i = i + 1) begin
        for (j = 0; j < 16; j = j + 1) begin
            A = i;
            B = j;
            #10; // Delay for simulation purposes
            
            // Write A, B, and R to the file
            $fdisplay(file_id, "A = %d, B = %d, R = %d", A, B, R);
        end
    end
    
    // Close the file
    $fclose(file_id);
    
    // Finish simulation after all iterations
    $finish;
end

endmodule

array_normal_84/Arraymul_eight_four_tb.vcd
$date
	Fri Mar 15 14:28:49 2024
$end
$version
	Icarus Verilog
$end
$timescale
	1ns
$end
$scope module Arraymul_eight_four_tb $end
$var wire 12 ! R [11:0] $end
$var reg 8 " A [7:0] $end
$var reg 4 # B [3:0] $end
$var integer 32 $ file_id [31:0] $end
$var integer 32 % i [31:0] $end
$var integer 32 & j [31:0] $end
$scope module uut $end
$var wire 8 ' A [7:0] $end
$var wire 4 ( B [3:0] $end
$var wire 65 ) s [64:0] $end
$var wire 8 * pp [7:0] $end
$var wire 65 + c [64:0] $end
$var wire 12 , R [11:0] $end
$scope module FA11 $end
$var wire 1 - a $end
$var wire 1 . b $end
$var wire 1 / cin $end
$var wire 1 0 cout $end
$var wire 1 1 sum $end
$upscope $end
$scope module FA12 $end
$var wire 1 2 a $end
$var wire 1 3 b $end
$var wire 1 4 cin $end
$var wire 1 5 cout $end
$var wire 1 6 sum $end
$upscope $end
$scope module FA13 $end
$var wire 1 7 a $end
$var wire 1 8 b $end
$var wire 1 9 cin $end
$var wire 1 : cout $end
$var wire 1 ; sum $end
$upscope $end
$scope module FA14 $end
$var wire 1 < a $end
$var wire 1 = b $end
$var wire 1 > cin $end
$var wire 1 ? cout $end
$var wire 1 @ sum $end
$upscope $end
$scope module FA15 $end
$var wire 1 A a $end
$var wire 1 B b $end
$var wire 1 C cin $end
$var wire 1 D cout $end
$var wire 1 E sum $end
$upscope $end
$scope module FA16 $end
$var wire 1 F a $end
$var wire 1 G b $end
$var wire 1 H cin $end
$var wire 1 I cout $end
$var wire 1 J sum $end
$upscope $end
$scope module FA17 $end
$var wire 1 K a $end
$var wire 1 L b $end
$var wire 1 M cin $end
$var wire 1 N cout $end
$var wire 1 O sum $end
$upscope $end
$scope module FA18 $end
$var wire 1 P a $end
$var wire 1 Q b $end
$var wire 1 R cin $end
$var wire 1 S cout $end
$var wire 1 T sum $end
$upscope $end
$scope module FA21 $end
$var wire 1 U a $end
$var wire 1 V b $end
$var wire 1 W cin $end
$var wire 1 X cout $end
$var wire 1 Y sum $end
$upscope $end
$scope module FA22 $end
$var wire 1 Z a $end
$var wire 1 [ b $end
$var wire 1 \ cin $end
$var wire 1 ] cout $end
$var wire 1 ^ sum $end
$upscope $end
$scope module FA23 $end
$var wire 1 _ a $end
$var wire 1 ` b $end
$var wire 1 a cin $end
$var wire 1 b cout $end
$var wire 1 c sum $end
$upscope $end
$scope module FA24 $end
$var wire 1 d a $end
$var wire 1 e b $end
$var wire 1 f cin $end
$var wire 1 g cout $end
$var wire 1 h sum $end
$upscope $end
$scope module FA25 $end
$var wire 1 i a $end
$var wire 1 j b $end
$var wire 1 k cin $end
$var wire 1 l cout $end
$var wire 1 m sum $end
$upscope $end
$scope module FA26 $end
$var wire 1 n a $end
$var wire 1 o b $end
$var wire 1 p cin $end
$var wire 1 q cout $end
$var wire 1 r sum $end
$upscope $end
$scope module FA27 $end
$var wire 1 s a $end
$var wire 1 t b $end
$var wire 1 u cin $end
$var wire 1 v cout $end
$var wire 1 w sum $end
$upscope $end
$scope module FA28 $end
$var wire 1 x a $end
$var wire 1 y b $end
$var wire 1 z cin $end
$var wire 1 { cout $end
$var wire 1 | sum $end
$upscope $end
$scope module FA31 $end
$var wire 1 } a $end
$var wire 1 ~ b $end
$var wire 1 !" cin $end
$var wire 1 "" cout $end
$var wire 1 #" sum $end
$upscope $end
$scope module FA32 $end
$var wire 1 $" a $end
$var wire 1 %" b $end
$var wire 1 &" cin $end
$var wire 1 '" cout $end
$var wire 1 (" sum $end
$upscope $end
$scope module FA33 $end
$var wire 1 )" a $end
$var wire 1 *" b $end
$var wire 1 +" cin $end
$var wire 1 ," cout $end
$var wire 1 -" sum $end
$upscope $end
$scope module FA34 $end
$var wire 1 ." a $end
$var wire 1 /" b $end
$var wire 1 0" cin $end
$var wire 1 1" cout $end
$var wire 1 2" sum $end
$upscope $end
$scope module FA35 $end
$var wire 1 3" a $end
$var wire 1 4" b $end
$var wire 1 5" cin $end
$var wire 1 6" cout $end
$var wire 1 7" sum $end
$upscope $end
$scope module FA36 $end
$var wire 1 8" a $end
$var wire 1 9" b $end
$var wire 1 :" cin $end
$var wire 1 ;" cout $end
$var wire 1 <" sum $end
$upscope $end
$scope module FA37 $end
$var wire 1 =" a $end
$var wire 1 >" b $end
$var wire 1 ?" cin $end
$var wire 1 @" cout $end
$var wire 1 A" sum $end
$upscope $end
$scope module FA38 $end
$var wire 1 B" a $end
$var wire 1 C" b $end
$var wire 1 D" cin $end
$var wire 1 E" cout $end
$var wire 1 F" sum $end
$upscope $end
$scope module PP01 $end
$var wire 1 G" c $end
$var wire 1 H" d $end
$var wire 1 I" pc $end
$upscope $end
$scope module PP02 $end
$var wire 1 J" c $end
$var wire 1 K" d $end
$var wire 1 L" pc $end
$upscope $end
$scope module PP03 $end
$var wire 1 M" c $end
$var wire 1 N" d $end
$var wire 1 O" pc $end
$upscope $end
$scope module PP04 $end
$var wire 1 P" c $end
$var wire 1 Q" d $end
$var wire 1 R" pc $end
$upscope $end
$scope module PP05 $end
$var wire 1 S" c $end
$var wire 1 T" d $end
$var wire 1 U" pc $end
$upscope $end
$scope module PP06 $end
$var wire 1 V" c $end
$var wire 1 W" d $end
$var wire 1 X" pc $end
$upscope $end
$scope module PP07 $end
$var wire 1 Y" c $end
$var wire 1 Z" d $end
$var wire 1 [" pc $end
$upscope $end
$scope module PP08 $end
$var wire 1 \" c $end
$var wire 1 ]" d $end
$var wire 1 ^" pc $end
$upscope $end
$upscope $end
$upscope $end
$enddefinitions $end
$comment Show the parameter values. $end
$dumpall
$end
#0
$dumpvars
0^"
0]"
0\"
0["
0Z"
0Y"
0X"
0W"
0V"
0U"
0T"
0S"
0R"
0Q"
0P"
0O"
0N"
0M"
0L"
0K"
0J"
0I"
0H"
0G"
0F"
0E"
0D"
0C"
0B"
0A"
0@"
0?"
0>"
0="
0<"
0;"
0:"
09"
08"
07"
06"
05"
04"
03"
02"
01"
00"
0/"
0."
0-"
0,"
0+"
0*"
0)"
0("
0'"
0&"
0%"
0$"
0#"
0""
0!"
0~
0}
0|
0{
0z
0y
0x
0w
0v
0u
0t
0s
0r
0q
0p
0o
0n
0m
0l
0k
0j
0i
0h
0g
0f
0e
0d
0c
0b
0a
0`
0_
0^
0]
0\
0[
0Z
0Y
0X
0W
0V
0U
0T
0S
0R
0Q
0P
0O
0N
0M
0L
0K
0J
0I
0H
0G
0F
0E
0D
0C
0B
0A
0@
0?
0>
0=
0<
0;
0:
09
08
07
06
05
04
03
02
01
00
0/
0.
0-
b0 ,
bz000000000000000000000000 +
b0 *
bz000000000000000000000000 )
b0 (
b0 '
b0 &
b0 %
b10000000000000000000000000000011 $
b0 #
b0 "
b0 !
$end
#10
1H"
1K"
1N"
1Q"
1T"
1W"
1Z"
1]"
b1 #
b1 (
b1 &
#20
0H"
0K"
0N"
0Q"
0T"
0W"
0Z"
0]"
b10 #
b10 (
b10 &
#30
1H"
1K"
1N"
1Q"
1T"
1W"
1Z"
1]"
b11 #
b11 (
b11 &
#40
0H"
0K"
0N"
0Q"
0T"
0W"
0Z"
0]"
b100 #
b100 (
b100 &
#50
1H"
1K"
1N"
1Q"
1T"
1W"
1Z"
1]"
b101 #
b101 (
b101 &
#60
0H"
0K"
0N"
0Q"
0T"
0W"
0Z"
0]"
b110 #
b110 (
b110 &
#70
1H"
1K"
1N"
1Q"
1T"
1W"
1Z"
1]"
b111 #
b111 (
b111 &
#80
0H"
0K"
0N"
0Q"
0T"
0W"
0Z"
0]"
b1000 #
b1000 (
b1000 &
#90
1H"
1K"
1N"
1Q"
1T"
1W"
1Z"
1]"
b1001 #
b1001 (
b1001 &
#100
0H"
0K"
0N"
0Q"
0T"
0W"
0Z"
0]"
b1010 #
b1010 (
b1010 &
#110
1H"
1K"
1N"
1Q"
1T"
1W"
1Z"
1]"
b1011 #
b1011 (
b1011 &
#120
0H"
0K"
0N"
0Q"
0T"
0W"
0Z"
0]"
b1100 #
b1100 (
b1100 &
#130
1H"
1K"
1N"
1Q"
1T"
1W"
1Z"
1]"
b1101 #
b1101 (
b1101 &
#140
0H"
0K"
0N"
0Q"
0T"
0W"
0Z"
0]"
b1110 #
b1110 (
b1110 &
#150
1H"
1K"
1N"
1Q"
1T"
1W"
1Z"
1]"
b1111 #
b1111 (
b1111 &
#160
0H"
0K"
0N"
0Q"
0T"
0W"
0Z"
0]"
1G"
b0 #
b0 (
b1 "
b1 '
b1 %
b0 &
#170
b1 !
b1 ,
b1 *
1I"
1H"
1K"
1N"
1Q"
1T"
1W"
1Z"
1]"
b1 #
b1 (
b1 &
#180
bz000000000000000000000001 )
11
b10 !
b10 ,
b0 *
0I"
1-
0H"
0K"
0N"
0Q"
0T"
0W"
0Z"
0]"
b10 #
b10 (
b10 &
#190
b11 !
b11 ,
b1 *
1I"
1H"
1K"
1N"
1Q"
1T"
1W"
1Z"
1]"
b11 #
b11 (
b11 &
#200
01
bz000000000000000100000000 )
1Y
b100 !
b100 ,
b0 *
0I"
0-
1U
0H"
0K"
0N"
0Q"
0T"
0W"
0Z"
0]"
b100 #
b100 (
b100 &
#210
b101 !
b101 ,
b1 *
1I"
1H"
1K"
1N"
1Q"
1T"
1W"
1Z"
1]"
b101 #
b101 (
b101 &
#220
bz000000000000000100000001 )
11
b110 !
b110 ,
b0 *
0I"
1-
0H"
0K"
0N"
0Q"
0T"
0W"
0Z"
0]"
b110 #
b110 (
b110 &
#230
b111 !
b111 ,
b1 *
1I"
1H"
1K"
1N"
1Q"
1T"
1W"
1Z"
1]"
b111 #
b111 (
b111 &
#240
01
0Y
bz000000010000000000000000 )
1#"
b1000 !
b1000 ,
b0 *
0I"
0-
0U
1}
0H"
0K"
0N"
0Q"
0T"
0W"
0Z"
0]"
b1000 #
b1000 (
b1000 &
#250
b1001 !
b1001 ,
b1 *
1I"
1H"
1K"
1N"
1Q"
1T"
1W"
1Z"
1]"
b1001 #
b1001 (
b1001 &
#260
bz000000010000000000000001 )
11
b1010 !
b1010 ,
b0 *
0I"
1-
0H"
0K"
0N"
0Q"
0T"
0W"
0Z"
0]"
b1010 #
b1010 (
b1010 &
#270
b1011 !
b1011 ,
b1 *
1I"
1H"
1K"
1N"
1Q"
1T"
1W"
1Z"
1]"
b1011 #
b1011 (
b1011 &
#280
01
bz000000010000000100000000 )
1Y
b1100 !
b1100 ,
b0 *
0I"
0-
1U
0H"
0K"
0N"
0Q"
0T"
0W"
0Z"
0]"
b1100 #
b1100 (
b1100 &
#290
b1101 !
b1101 ,
b1 *
1I"
1H"
1K"
1N"
1Q"
1T"
1W"
1Z"
1]"
b1101 #
b1101 (
b1101 &
#300
bz000000010000000100000001 )
11
b1110 !
b1110 ,
b0 *
0I"
1-
0H"
0K"
0N"
0Q"
0T"
0W"
0Z"
0]"
b1110 #
b1110 (
b1110 &
#310
b1111 !
b1111 ,
b1 *
1I"
1H"
1K"
1N"
1Q"
1T"
1W"
1Z"
1]"
b1111 #
b1111 (
b1111 &
#320
01
0Y
bz000000000000000000000000 )
0#"
b0 !
b0 ,
b0 *
0I"
0-
0U
0}
0H"
0K"
0N"
0Q"
0T"
0W"
0Z"
0]"
0G"
1J"
b0 #
b0 (
b10 "
b10 '
b10 %
b0 &
#330
b10 !
b10 ,
bz000000000000000000000001 )
11
1.
b10 *
1L"
1H"
1K"
1N"
1Q"
1T"
1W"
1Z"
1]"
b1 #
b1 (
b1 &
#340
1Y
b100 !
b100 ,
01
1V
bz000000000000000100000010 )
16
0.
b0 *
0L"
12
0H"
0K"
0N"
0Q"
0T"
0W"
0Z"
0]"
b10 #
b10 (
b10 &
#350
b110 !
b110 ,
bz000000000000000100000011 )
11
1.
b10 *
1L"
1H"
1K"
1N"
1Q"
1T"
1W"
1Z"
1]"
b11 #
b11 (
b11 &
#360
0Y
1#"
b1000 !
b1000 ,
01
0V
1~
06
bz000000010000001000000000 )
1^
0.
b0 *
0L"
02
1Z
0H"
0K"
0N"
0Q"
0T"
0W"
0Z"
0]"
b100 #
b100 (
b100 &
#370
b1010 !
b1010 ,
bz000000010000001000000001 )
11
1.
b10 *
1L"
1H"
1K"
1N"
1Q"
1T"
1W"
1Z"
1]"
b101 #
b101 (
b101 &
#380
1Y
b1100 !
b1100 ,
01
1V
bz000000010000001100000010 )
16
0.
b0 *
0L"
12
0H"
0K"
0N"
0Q"
0T"
0W"
0Z"
0]"
b110 #
b110 (
b110 &
#390
b1110 !
b1110 ,
bz000000010000001100000011 )
11
1.
b10 *
1L"
1H"
1K"
1N"
1Q"
1T"
1W"
1Z"
1]"
b111 #
b111 (
b111 &
#400
0Y
0#"
01
0V
0~
b10000 !
b10000 ,
06
0^
bz000000100000000000000000 )
1("
0.
b0 *
0L"
02
0Z
1$"
0H"
0K"
0N"
0Q"
0T"
0W"
0Z"
0]"
b1000 #
b1000 (
b1000 &
#410
b10010 !
b10010 ,
bz000000100000000000000001 )
11
1.
b10 *
1L"
1H"
1K"
1N"
1Q"
1T"
1W"
1Z"
1]"
b1001 #
b1001 (
b1001 &
#420
1Y
b10100 !
b10100 ,
01
1V
bz000000100000000100000010 )
16
0.
b0 *
0L"
12
0H"
0K"
0N"
0Q"
0T"
0W"
0Z"
0]"
b1010 #
b1010 (
b1010 &
#430
b10110 !
b10110 ,
bz000000100000000100000011 )
11
1.
b10 *
1L"
1H"
1K"
1N"
1Q"
1T"
1W"
1Z"
1]"
b1011 #
b1011 (
b1011 &
#440
0Y
1#"
b11000 !
b11000 ,
01
0V
1~
06
bz000000110000001000000000 )
1^
0.
b0 *
0L"
02
1Z
0H"
0K"
0N"
0Q"
0T"
0W"
0Z"
0]"
b1100 #
b1100 (
b1100 &
#450
b11010 !
b11010 ,
bz000000110000001000000001 )
11
1.
b10 *
1L"
1H"
1K"
1N"
1Q"
1T"
1W"
1Z"
1]"
b1101 #
b1101 (
b1101 &
#460
1Y
b11100 !
b11100 ,
01
1V
bz000000110000001100000010 )
16
0.
b0 *
0L"
12
0H"
0K"
0N"
0Q"
0T"
0W"
0Z"
0]"
b1110 #
b1110 (
b1110 &
#470
b11110 !
b11110 ,
bz000000110000001100000011 )
11
1.
b10 *
1L"
1H"
1K"
1N"
1Q"
1T"
1W"
1Z"
1]"
b1111 #
b1111 (
b1111 &
#480
0Y
0#"
01
0V
0~
b0 !
b0 ,
06
0^
bz000000000000000000000000 )
0("
0.
b0 *
0L"
02
0Z
0$"
0H"
0K"
0N"
0Q"
0T"
0W"
0Z"
0]"
1G"
b0 #
b0 (
b11 "
b11 '
b11 %
b0 &
#490
bz000000000000000000000001 )
11
b11 !
b11 ,
1.
1I"
b11 *
1L"
1H"
1K"
1N"
1Q"
1T"
1W"
1Z"
1]"
b1 #
b1 (
b1 &
#500
0#"
0~
0^
0[
0;
09
05
1Y
04
bz000000000000000000000000 +
00
1V
11
bz000000000000000100000011 )
16
b110 !
b110 ,
0.
0I"
b0 *
0L"
1-
12
0H"
0K"
0N"
0Q"
0T"
0W"
0Z"
0]"
b10 #
b10 (
b10 &
#510
1#"
1~
1^
1[
0Y
1;
19
0V
15
06
14
bz000000000000000000000011 +
10
bz000000010000001000000100 )
01
b1001 !
b1001 ,
1.
1I"
b11 *
1L"
1H"
1K"
1N"
1Q"
1T"
1W"
1Z"
1]"
b11 #
b11 (
b11 &
#520
0("
0\
0X
0%"
0[
1#"
0c
04
0;
0a
00
0V
09
1~
0]
01
06
bz000000000000000000000000 +
05
1Y
bz000000010000001100000000 )
1^
b1100 !
b1100 ,
0.
0I"
b0 *
0L"
0-
02
1U
1Z
0H"
0K"
0N"
0Q"
0T"
0W"
0Z"
0]"
b100 #
b100 (
b100 &
#530
bz000000010000001100000001 )
11
b1111 !
b1111 ,
1.
1I"
b11 *
1L"
1H"
1K"
1N"
1Q"
1T"
1W"
1Z"
1]"
b101 #
b101 (
b101 &
#540
1("
1%"
0#"
1c
1a
0[
0~
1]
0;
0^
09
1\
05
1X
0Y
04
bz000000000000001100000000 +
00
1V
11
bz000000100000010000000011 )
16
b10010 !
b10010 ,
0.
0I"
b0 *
0L"
1-
12
0H"
0K"
0N"
0Q"
0T"
0W"
0Z"
0]"
b110 #
b110 (
b110 &
#550
0\
0X
1[
1Y
1;
19
0V
15
06
14
bz000000000000001000000011 +
10
bz000000100000010100000100 )
01
b10101 !
b10101 ,
1.
1I"
b11 *
1L"
1H"
1K"
1N"
1Q"
1T"
1W"
1Z"
1]"
b111 #
b111 (
b111 &
#560
0&"
0""
0%"
0[
0c
0-"
04
0;
0a
0+"
00
0V
09
0~
0]
0'"
01
06
bz000000000000000000000000 +
05
0Y
0^
1#"
bz000000110000000000000000 )
1("
b11000 !
b11000 ,
0.
0I"
b0 *
0L"
0-
02
0U
0Z
1}
1$"
0H"
0K"
0N"
0Q"
0T"
0W"
0Z"
0]"
b1000 #
b1000 (
b1000 &
#570
bz000000110000000000000001 )
11
b11011 !
b11011 ,
1.
1I"
b11 *
1L"
1H"
1K"
1N"
1Q"
1T"
1W"
1Z"
1]"
b1001 #
b1001 (
b1001 &
#580
0-"
0+"
0'"
1("
0&"
0""
1#"
0~
0^
0[
0;
09
05
1Y
04
bz000000000000000000000000 +
00
1V
11
bz000000110000000100000011 )
16
b11110 !
b11110 ,
0.
0I"
b0 *
0L"
1-
12
0H"
0K"
0N"
0Q"
0T"
0W"
0Z"
0]"
b1010 #
b1010 (
b1010 &
#590
1-"
1+"
1'"
0("
1&"
1""
0#"
1~
1^
1[
0Y
1;
19
0V
15
06
14
bz000000110000000000000011 +
10
bz000001000000001000000100 )
01
b100001 !
b100001 ,
1.
1I"
b11 *
1L"
1H"
1K"
1N"
1Q"
1T"
1W"
1Z"
1]"
b1011 #
b1011 (
b1011 &
#600
0\
1&"
0X
1""
0%"
0[
0#"
0c
04
0;
0a
00
0V
09
1~
0]
01
06
bz000000110000000000000000 +
05
1Y
bz000001000000001100000000 )
1^
b100100 !
b100100 ,
0.
0I"
b0 *
0L"
0-
02
1U
1Z
0H"
0K"
0N"
0Q"
0T"
0W"
0Z"
0]"
b1100 #
b1100 (
b1100 &
#610
bz000001000000001100000001 )
11
b100111 !
b100111 ,
1.
1I"
b11 *
1L"
1H"
1K"
1N"
1Q"
1T"
1W"
1Z"
1]"
b1101 #
b1101 (
b1101 &
#620
0&"
0""
1%"
1#"
1c
1a
0[
0~
1]
0;
0^
09
1\
05
1X
0Y
04
bz000000100000001100000000 +
00
1V
11
bz000001010000010000000011 )
16
b101010 !
b101010 ,
0.
0I"
b0 *
0L"
1-
12
0H"
0K"
0N"
0Q"
0T"
0W"
0Z"
0]"
b1110 #
b1110 (
b1110 &
#630
0\
0X
1[
1Y
1;
19
0V
15
06
14
bz000000100000001000000011 +
10
bz000001010000010100000100 )
01
b101101 !
b101101 ,
1.
1I"
b11 *
1L"
1H"
1K"
1N"
1Q"
1T"
1W"
1Z"
1]"
b1111 #
b1111 (
b1111 &
#640
0%"
0[
0c
0-"
04
0;
0a
0+"
00
0V
09
0~
0]
0'"
01
06
bz000000000000000000000000 +
05
0Y
0^
0#"
bz000000000000000000000000 )
0("
b0 !
b0 ,
0.
0I"
b0 *
0L"
0-
02
0U
0Z
0}
0$"
0H"
0K"
0N"
0Q"
0T"
0W"
0Z"
0]"
0G"
0J"
1M"
b0 #
b0 (
b100 "
b100 '
b100 %
b0 &
#650
b100 !
b100 ,
1Y
1V
bz000000000000000100000010 )
16
13
b100 *
1O"
1H"
1K"
1N"
1Q"
1T"
1W"
1Z"
1]"
b1 #
b1 (
b1 &
#660
1#"
b1000 !
b1000 ,
0Y
1~
1^
0V
06
1[
bz000000010000001000000100 )
1;
03
b0 *
0O"
17
0H"
0K"
0N"
0Q"
0T"
0W"
0Z"
0]"
b10 #
b10 (
b10 &
#670
b1100 !
b1100 ,
1Y
1V
bz000000010000001100000110 )
16
13
b100 *
1O"
1H"
1K"
1N"
1Q"
1T"
1W"
1Z"
1]"
b11 #
b11 (
b11 &
#680
0#"
0Y
0~
b10000 !
b10000 ,
0^
1("
0V
06
0[
1%"
0;
bz000000100000010000000000 )
1c
03
b0 *
0O"
07
1_
0H"
0K"
0N"
0Q"
0T"
0W"
0Z"
0]"
b100 #
b100 (
b100 &
#690
b10100 !
b10100 ,
1Y
1V
bz000000100000010100000010 )
16
13
b100 *
1O"
1H"
1K"
1N"
1Q"
1T"
1W"
1Z"
1]"
b101 #
b101 (
b101 &
#700
1#"
b11000 !
b11000 ,
0Y
1~
1^
0V
06
1[
bz000000110000011000000100 )
1;
03
b0 *
0O"
17
0H"
0K"
0N"
0Q"
0T"
0W"
0Z"
0]"
b110 #
b110 (
b110 &
#710
b11100 !
b11100 ,
1Y
1V
bz000000110000011100000110 )
16
13
b100 *
1O"
1H"
1K"
1N"
1Q"
1T"
1W"
1Z"
1]"
b111 #
b111 (
b111 &
#720
0#"
0Y
0~
0^
0("
0V
06
0[
0%"
b100000 !
b100000 ,
0;
0c
bz000001000000000000000000 )
1-"
03
b0 *
0O"
07
0_
1)"
0H"
0K"
0N"
0Q"
0T"
0W"
0Z"
0]"
b1000 #
b1000 (
b1000 &
#730
b100100 !
b100100 ,
1Y
1V
bz000001000000000100000010 )
16
13
b100 *
1O"
1H"
1K"
1N"
1Q"
1T"
1W"
1Z"
1]"
b1001 #
b1001 (
b1001 &
#740
1#"
b101000 !
b101000 ,
0Y
1~
1^
0V
06
1[
bz000001010000001000000100 )
1;
03
b0 *
0O"
17
0H"
0K"
0N"
0Q"
0T"
0W"
0Z"
0]"
b1010 #
b1010 (
b1010 &
#750
b101100 !
b101100 ,
1Y
1V
bz000001010000001100000110 )
16
13
b100 *
1O"
1H"
1K"
1N"
1Q"
1T"
1W"
1Z"
1]"
b1011 #
b1011 (
b1011 &
#760
0#"
0Y
0~
b110000 !
b110000 ,
0^
1("
0V
06
0[
1%"
0;
bz000001100000010000000000 )
1c
03
b0 *
0O"
07
1_
0H"
0K"
0N"
0Q"
0T"
0W"
0Z"
0]"
b1100 #
b1100 (
b1100 &
#770
b110100 !
b110100 ,
1Y
1V
bz000001100000010100000010 )
16
13
b100 *
1O"
1H"
1K"
1N"
1Q"
1T"
1W"
1Z"
1]"
b1101 #
b1101 (
b1101 &
#780
1#"
b111000 !
b111000 ,
0Y
1~
1^
0V
06
1[
bz000001110000011000000100 )
1;
03
b0 *
0O"
17
0H"
0K"
0N"
0Q"
0T"
0W"
0Z"
0]"
b1110 #
b1110 (
b1110 &
#790
b111100 !
b111100 ,
1Y
1V
bz000001110000011100000110 )
16
13
b100 *
1O"
1H"
1K"
1N"
1Q"
1T"
1W"
1Z"
1]"
b1111 #
b1111 (
b1111 &
#800
0#"
0Y
0~
0^
0("
0V
06
0[
0%"
b0 !
b0 ,
0;
0c
bz000000000000000000000000 )
0-"
03
b0 *
0O"
07
0_
0)"
0H"
0K"
0N"
0Q"
0T"
0W"
0Z"
0]"
1G"
b0 #
b0 (
b101 "
b101 '
b101 %
b0 &
#810
1Y
1V
bz000000000000000100000010 )
16
b101 !
b101 ,
13
1I"
b101 *
1O"
1H"
1K"
1N"
1Q"
1T"
1W"
1Z"
1]"
b1 #
b1 (
b1 &
#820
1#"
0Y
1~
1^
0V
06
1[
11
bz000000010000001000000101 )
1;
b1010 !
b1010 ,
03
0I"
b0 *
0O"
1-
17
0H"
0K"
0N"
0Q"
0T"
0W"
0Z"
0]"
b10 #
b10 (
b10 &
#830
1Y
1V
bz000000010000001100000111 )
16
b1111 !
b1111 ,
13
1I"
b101 *
1O"
1H"
1K"
1N"
1Q"
1T"
1W"
1Z"
1]"
b11 #
b11 (
b11 &
#840
0#"
0~
0^
1("
0V
0\
06
0[
bz000000000000000000000000 +
0X
1%"
01
0;
1Y
bz000000100000010100000000 )
1c
b10100 !
b10100 ,
03
0I"
b0 *
0O"
0-
07
1U
1_
0H"
0K"
0N"
0Q"
0T"
0W"
0Z"
0]"
b100 #
b100 (
b100 &
#850
1#"
1~
1^
1\
bz000000000000000100000000 +
1X
0Y
1V
bz000000110000011000000010 )
16
b11001 !
b11001 ,
13
1I"
b101 *
1O"
1H"
1K"
1N"
1Q"
1T"
1W"
1Z"
1]"
b101 #
b101 (
b101 &
#860
0-"
0*"
1("
0h
0f
1%"
0b
0\
1#"
1c
0X
0a
1Y
1~
bz000000000000000000000000 +
0]
1^
0V
06
1[
11
bz000000110000011100000101 )
1;
b11110 !
b11110 ,
03
0I"
b0 *
0O"
1-
17
0H"
0K"
0N"
0Q"
0T"
0W"
0Z"
0]"
b110 #
b110 (
b110 &
#870
1-"
1*"
0("
1h
1f
0%"
1b
0c
0#"
1a
1]
0~
0^
1\
bz000000000000011100000000 +
1X
0Y
1V
bz000001000000100000000111 )
16
b100011 !
b100011 ,
13
1I"
b101 *
1O"
1H"
1K"
1N"
1Q"
1T"
1W"
1Z"
1]"
b111 #
b111 (
b111 &
#880
0a
0]
0("
0*"
02"
0V
0\
0h
00"
06
0[
0X
0%"
0f
0,"
01
0;
0Y
0c
bz000000000000000000000000 +
0b
1#"
bz000001010000000000000000 )
1-"
b101000 !
b101000 ,
03
0I"
b0 *
0O"
0-
07
0U
0_
1}
1)"
0H"
0K"
0N"
0Q"
0T"
0W"
0Z"
0]"
b1000 #
b1000 (
b1000 &
#890
1Y
1V
bz000001010000000100000010 )
16
b101101 !
b101101 ,
13
1I"
b101 *
1O"
1H"
1K"
1N"
1Q"
1T"
1W"
1Z"
1]"
b1001 #
b1001 (
b1001 &
#900
1("
1&"
bz000000010000000000000000 +
1""
0#"
0Y
1~
1^
0V
06
1[
11
bz000001100000001000000101 )
1;
b110010 !
b110010 ,
03
0I"
b0 *
0O"
1-
17
0H"
0K"
0N"
0Q"
0T"
0W"
0Z"
0]"
b1010 #
b1010 (
b1010 &
